igrepper/__init__.py
igrepper/igrepper.py
igrepper-0.0.2.data/scripts/igrepper
igrepper-0.0.2.dist-info/DESCRIPTION.rst
igrepper-0.0.2.dist-info/METADATA
igrepper-0.0.2.dist-info/RECORD
igrepper-0.0.2.dist-info/WHEEL
igrepper-0.0.2.dist-info/metadata.json
igrepper-0.0.2.dist-info/top_level.txt
